{"name":"build-javascript","namedChunkGroups":{"polyfill":{"name":"polyfill","assets":[{"name":"webpack-runtime-7f587b471e4f4f0dd61c.js","size":5083},{"name":"polyfill-95829936ee7548bb8900.js","size":85010}],"filteredAssets":0,"assetsSize":90093,"filteredAuxiliaryAssets":2,"auxiliaryAssetsSize":230141},"app":{"name":"app","assets":[{"name":"webpack-runtime-7f587b471e4f4f0dd61c.js","size":5083},{"name":"styles.81f6f74741163a2dfaaf.css","size":1145779},{"name":"framework-86dbb547eaeef35c168c.js","size":24996},{"name":"3f943334-a6d14311d76801ecea87.js","size":12949},{"name":"379b34f3-e85ac1b28f07dc401ea0.js","size":17006},{"name":"ff106bf9-6372911072cd20fb88e2.js","size":15990},{"name":"bca8bde3-cca3a92dc4e179611068.js","size":19506},{"name":"app-f09c6ce8a3b2c6c95535.js","size":272668}],"filteredAssets":0,"assetsSize":1513977,"filteredAuxiliaryAssets":7,"auxiliaryAssetsSize":1290017},"component---node-modules-adobe-gatsby-theme-aio-src-pages-404-md":{"name":"component---node-modules-adobe-gatsby-theme-aio-src-pages-404-md","assets":[{"name":"styles.81f6f74741163a2dfaaf.css","size":1145779},{"name":"b6f3ea4c-7dac76507b5da95dae3e.js","size":9053},{"name":"5e65052d-50b4ec327e78c2a479ea.js","size":13639},{"name":"8b61fb39-87158335ee8cdf641bac.js","size":10960},{"name":"ea88be26-8999613817adf3b87e86.js","size":297460},{"name":"f5cc1685-72f895e76ade7ce17a4d.js","size":7214},{"name":"1e479c3f-79423c8e76c46b38b5ac.js","size":6568},{"name":"490477d6-93b0890957134270678c.js","size":5931},{"name":"2dee68d8-39b3c2afd54772b6dfb8.js","size":7962},{"name":"c9f1e04f-26c11ab1a73df1da48e4.js","size":5764},{"name":"commons-d9d9fc1e3b4000ea6fc0.js","size":869250},{"name":"component---node-modules-adobe-gatsby-theme-aio-src-pages-404-md-e3ea35654459774cc70b.js","size":1096}],"filteredAssets":0,"assetsSize":2380676,"filteredAuxiliaryAssets":11,"auxiliaryAssetsSize":3225104},"component---src-pages-index-md":{"name":"component---src-pages-index-md","assets":[{"name":"styles.81f6f74741163a2dfaaf.css","size":1145779},{"name":"b6f3ea4c-7dac76507b5da95dae3e.js","size":9053},{"name":"5e65052d-50b4ec327e78c2a479ea.js","size":13639},{"name":"8b61fb39-87158335ee8cdf641bac.js","size":10960},{"name":"ea88be26-8999613817adf3b87e86.js","size":297460},{"name":"f5cc1685-72f895e76ade7ce17a4d.js","size":7214},{"name":"1e479c3f-79423c8e76c46b38b5ac.js","size":6568},{"name":"490477d6-93b0890957134270678c.js","size":5931},{"name":"2dee68d8-39b3c2afd54772b6dfb8.js","size":7962},{"name":"c9f1e04f-26c11ab1a73df1da48e4.js","size":5764},{"name":"commons-d9d9fc1e3b4000ea6fc0.js","size":869250},{"name":"component---src-pages-index-md-05e1fcdf2be57421832d.js","size":14165}],"filteredAssets":0,"assetsSize":2393745,"filteredAuxiliaryAssets":11,"auxiliaryAssetsSize":3248529}},"assetsByChunkName":{"polyfill":["webpack-runtime-7f587b471e4f4f0dd61c.js","polyfill-95829936ee7548bb8900.js"],"app":["webpack-runtime-7f587b471e4f4f0dd61c.js","styles.81f6f74741163a2dfaaf.css","framework-86dbb547eaeef35c168c.js","3f943334-a6d14311d76801ecea87.js","379b34f3-e85ac1b28f07dc401ea0.js","ff106bf9-6372911072cd20fb88e2.js","bca8bde3-cca3a92dc4e179611068.js","app-f09c6ce8a3b2c6c95535.js"],"component---node-modules-adobe-gatsby-theme-aio-src-pages-404-md":["styles.81f6f74741163a2dfaaf.css","b6f3ea4c-7dac76507b5da95dae3e.js","5e65052d-50b4ec327e78c2a479ea.js","8b61fb39-87158335ee8cdf641bac.js","ea88be26-8999613817adf3b87e86.js","f5cc1685-72f895e76ade7ce17a4d.js","1e479c3f-79423c8e76c46b38b5ac.js","490477d6-93b0890957134270678c.js","2dee68d8-39b3c2afd54772b6dfb8.js","c9f1e04f-26c11ab1a73df1da48e4.js","commons-d9d9fc1e3b4000ea6fc0.js","component---node-modules-adobe-gatsby-theme-aio-src-pages-404-md-e3ea35654459774cc70b.js"],"component---src-pages-index-md":["styles.81f6f74741163a2dfaaf.css","b6f3ea4c-7dac76507b5da95dae3e.js","5e65052d-50b4ec327e78c2a479ea.js","8b61fb39-87158335ee8cdf641bac.js","ea88be26-8999613817adf3b87e86.js","f5cc1685-72f895e76ade7ce17a4d.js","1e479c3f-79423c8e76c46b38b5ac.js","490477d6-93b0890957134270678c.js","2dee68d8-39b3c2afd54772b6dfb8.js","c9f1e04f-26c11ab1a73df1da48e4.js","commons-d9d9fc1e3b4000ea6fc0.js","component---src-pages-index-md-05e1fcdf2be57421832d.js"]},"childAssetsByChunkName":{}}